cutils/__init__.py
cutils/cutils.py
cutils/py.typed
pycutils-0.1.1.dist-info/LICENSE
pycutils-0.1.1.dist-info/METADATA
pycutils-0.1.1.dist-info/WHEEL
pycutils-0.1.1.dist-info/top_level.txt
pycutils-0.1.1.dist-info/RECORD
