Metadata-Version: 2.1
Name: pycutils
Version: 0.1.1
Summary: A list of python utilities
Home-page: https://github.com/CangyuanLi/cutils
Author: Cangyuan Li
Author-email: everest229@gmail.com
Project-URL: Bug Tracker, https://github.com/CangyuanLi/cutils/issues
Classifier: Programming Language :: Python :: 3
Classifier: License :: OSI Approved :: MIT License
Classifier: Operating System :: OS Independent
Requires-Python: >=3.6
License-File: LICENSE
